polaris_cli/__init__.py
polaris_cli/cli.py
polaris_cli/log_monitor.py
polaris_cli/network_handler.py
polaris_cli/register.py
polaris_cli/repo_manager.py
polaris_cli/start.py
polaris_cli/view_pod.py
polaris_cli_tool-1.0.9.dist-info/METADATA
polaris_cli_tool-1.0.9.dist-info/WHEEL
polaris_cli_tool-1.0.9.dist-info/entry_points.txt
polaris_cli_tool-1.0.9.dist-info/top_level.txt
polaris_cli_tool-1.0.9.dist-info/RECORD
